odoo/addons/l10n_ca_cnae/README.rst
odoo/addons/l10n_ca_cnae/__init__.py
odoo/addons/l10n_ca_cnae/__manifest__.py
odoo/addons/l10n_ca_cnae/data/res.partner.industry.cat.csv
odoo/addons/l10n_ca_cnae/i18n/ca.po
odoo/addons/l10n_ca_cnae/i18n/l10n_ca_cnae.pot
odoo/addons/l10n_ca_cnae/i18n/l10n_es_cnae.pot
odoo/addons/l10n_ca_cnae/readme/CONTRIBUTORS.md
odoo/addons/l10n_ca_cnae/readme/DESCRIPTION.md
odoo/addons/l10n_ca_cnae/readme/INSTALL.md
odoo/addons/l10n_ca_cnae/readme/USAGE.md
odoo/addons/l10n_ca_cnae/static/description/icon.png
odoo/addons/l10n_ca_cnae/static/description/index.html
odoo/addons/l10n_ca_cnae/tests/__init__.py
odoo/addons/l10n_ca_cnae/tests/test_l10n_ca_cnae.py
odoo/addons/l10n_ca_cnae/wizard/__init__.py
odoo/addons/l10n_ca_cnae/wizard/res_partner_industry_eu_nace_wizard.py
odoo_addon_l10n_ca_cnae-17.0.1.0.0.2.dist-info/METADATA
odoo_addon_l10n_ca_cnae-17.0.1.0.0.2.dist-info/WHEEL
odoo_addon_l10n_ca_cnae-17.0.1.0.0.2.dist-info/top_level.txt
odoo_addon_l10n_ca_cnae-17.0.1.0.0.2.dist-info/RECORD
