Metadata-Version: 2.1
Name: odoo-addon-l10n_ca_cnae
Version: 17.0.1.0.0.2
Requires-Python: >=3.10
Requires-Dist: odoo-addon-l10n_es_cnae>=17.0dev,<17.1dev
Requires-Dist: odoo>=17.0a,<17.1dev
Summary: =?utf-8?q?Genera_la_traducci=C3=B3n_al_catal=C3=A1n_de_todos_los_c=C3=B3digos_Nace?=
Home-page: https://github.com/OCA/l10n-spain
License: AGPL-3
Author: Tecnativa, Odoo Community Association (OCA)
Author-email: support@odoo-community.org
Classifier: Programming Language :: Python
Classifier: Framework :: Odoo
Classifier: Framework :: Odoo :: 17.0
Classifier: License :: OSI Approved :: GNU Affero General Public License v3
